xlogs/__init__.py
xlogs/color_stream_handler.py
xlogs/config.ini
xlogs/xlog.py
xlogs/xlog2.py
xlogs/test/__init__.py
xlogs/test/test.py
xlogs-1.0.3.dist-info/LICENSE
xlogs-1.0.3.dist-info/METADATA
xlogs-1.0.3.dist-info/WHEEL
xlogs-1.0.3.dist-info/top_level.txt
xlogs-1.0.3.dist-info/RECORD
