Metadata-Version: 2.1
Name: xlogs
Version: 1.0.3
Summary: A logging toolkit
Home-page: https://github.com/txu2k8/python-xlogs
Author: tao.xu
Author-email: tao.xu2008@outlook.com
License: MIT
Keywords: python,logging,log
Platform: UNKNOWN
Classifier: Intended Audience :: Developers
Classifier: License :: OSI Approved :: MIT License
Classifier: Natural Language :: English
Classifier: Programming Language :: Python :: 3
Requires-Python: >=3.4.0
